MANIFEST.in
README.rst
client_test.py
setup.py
hypertable/__init__.py
hypertable/thriftclient.py
hypertable.egg-info/PKG-INFO
hypertable.egg-info/SOURCES.txt
hypertable.egg-info/dependency_links.txt
hypertable.egg-info/requires.txt
hypertable.egg-info/top_level.txt
hyperthrift/__init__.py
hyperthrift/gen/ClientService.py
hyperthrift/gen/__init__.py
hyperthrift/gen/constants.py
hyperthrift/gen/ttypes.py
hyperthrift/gen2/HqlService.py
hyperthrift/gen2/__init__.py
hyperthrift/gen2/constants.py
hyperthrift/gen2/ttypes.py
thrift/TMultiplexedProcessor.py
thrift/TSCons.py
thrift/TSerialization.py
thrift/TTornado.py
thrift/Thrift.py
thrift/__init__.py
thrift/protocol/TBase.py
thrift/protocol/TBinaryProtocol.py
thrift/protocol/TCompactProtocol.py
thrift/protocol/TJSONProtocol.py
thrift/protocol/TMultiplexedProtocol.py
thrift/protocol/TProtocol.py
thrift/protocol/TProtocolDecorator.py
thrift/protocol/__init__.py
thrift/server/THttpServer.py
thrift/server/TNonblockingServer.py
thrift/server/TProcessPoolServer.py
thrift/server/TServer.py
thrift/server/__init__.py
thrift/transport/THttpClient.py
thrift/transport/TSSLSocket.py
thrift/transport/TSocket.py
thrift/transport/TTransport.py
thrift/transport/TTwisted.py
thrift/transport/TZlibTransport.py
thrift/transport/__init__.py