Metadata-Version: 1.0
Name: hypertable
Version: 0.9.8.10
Summary: Python client for Hypertable
Home-page: http://hypertable.com/documentation/developer_guide/python/
Author: UNKNOWN
Author-email: UNKNOWN
License: GPLv3
Platform: UNKNOWN
